hosts/__init__.py
hosts/main.py
hosts_manager-0.2.8.dist-info/METADATA
hosts_manager-0.2.8.dist-info/WHEEL
hosts_manager-0.2.8.dist-info/entry_points.txt
hosts_manager-0.2.8.dist-info/top_level.txt
hosts_manager-0.2.8.dist-info/RECORD
