Metadata-Version: 2.1
Name: hosts-manager
Version: 0.2.8
Summary: A script to manage the /etc/hosts file.
Author-email: Friedjof Noweck <git@noweck.info>, Jason Taylor <jetaylor@gmail.com>
License: MIT
Project-URL: Homepage, https://github.com/Friedjof/hosts
Project-URL: Documentation, https://github.com/Friedjof/hosts/blob/main/README.md
Project-URL: Source, https://github.com/Friedjof/hosts
Project-URL: Tracker, https://github.com/Friedjof/hosts/issues
Classifier: Programming Language :: Python :: 3
Classifier: License :: OSI Approved :: MIT License
Classifier: Operating System :: OS Independent
Requires-Python: >=3.6
Requires-Dist: setuptools>=72.1.0
Requires-Dist: validators>=0.33.0
